tektra/__init__.py
tektra/cli.py
tektra/server.py
tektra/setup.py
tektra/app/__init__.py
tektra/app/config.py
tektra/app/database.py
tektra/app/dependencies.py
tektra/app/main.py
tektra/app/models/__init__.py
tektra/app/models/conversation.py
tektra/app/models/message.py
tektra/app/models/user.py
tektra/app/models/user_preferences.py
tektra/app/routers/__init__.py
tektra/app/routers/ai.py
tektra/app/routers/audio.py
tektra/app/routers/avatar.py
tektra/app/routers/camera.py
tektra/app/routers/conversations.py
tektra/app/routers/conversations_enhanced.py
tektra/app/routers/models.py
tektra/app/routers/preferences.py
tektra/app/routers/robot.py
tektra/app/routers/security.py
tektra/app/routers/websocket.py
tektra/app/security/__init__.py
tektra/app/security/anonymization.py
tektra/app/security/biometric_auth.py
tektra/app/security/key_derivation.py
tektra/app/security/vault_manager.py
tektra/app/services/__init__.py
tektra/app/services/ai_service.py
tektra/app/services/auto_installer.py
tektra/app/services/conversation_search_service.py
tektra/app/services/conversation_service.py
tektra/app/services/language_service.py
tektra/app/services/lip_sync_service.py
tektra/app/services/model_manager.py
tektra/app/services/phi4_service.py
tektra/app/services/preferences_service.py
tektra/app/services/security_service.py
tektra/app/services/tts_service.py
tektra/app/services/vad_service.py
tektra/app/services/whisper_service.py
tektra/frontend/404.html
tektra/frontend/favicon.ico
tektra/frontend/file.svg
tektra/frontend/globe.svg
tektra/frontend/index.html
tektra/frontend/index.txt
tektra/frontend/next.svg
tektra/frontend/vercel.svg
tektra/frontend/window.svg
tektra/frontend/404/index.html
tektra/frontend/_next/static/Ieo0CEC9U7QxZEgpVy1GX/_buildManifest.js
tektra/frontend/_next/static/Ieo0CEC9U7QxZEgpVy1GX/_ssgManifest.js
tektra/frontend/_next/static/WIx_auSG1NcxP4Aigr1W1/_buildManifest.js
tektra/frontend/_next/static/WIx_auSG1NcxP4Aigr1W1/_ssgManifest.js
tektra-0.9.16.dist-info/licenses/LICENSE
tektra-0.9.16.dist-info/METADATA
tektra-0.9.16.dist-info/WHEEL
tektra-0.9.16.dist-info/entry_points.txt
tektra-0.9.16.dist-info/top_level.txt
tektra-0.9.16.dist-info/RECORD
