Metadata-Version: 2.4
Name: tektra
Version: 0.9.16
Summary: Advanced AI assistant with 3D avatar, lip-sync, Microsoft Phi-4 Multimodal integration, biometric security, voice, vision, and robotics capabilities
Home-page: https://github.com/tektra/tektra
Author: Tektra Team
Author-email: Saorsa Labs <saorsalabs@gmail.com>
Maintainer-email: Saorsa Labs <saorsalabs@gmail.com>
License: MIT
Project-URL: Homepage, https://github.com/dirvine/tektra
Project-URL: Documentation, https://github.com/dirvine/tektra#readme
Project-URL: Repository, https://github.com/dirvine/tektra
Project-URL: Bug Reports, https://github.com/dirvine/tektra/issues
Keywords: ai,assistant,voice,vision,robotics,ml,chatbot,phi4,multimodal,speech-recognition,avatar,3d,lip-sync,biometric,security,tts
Classifier: Development Status :: 4 - Beta
Classifier: Intended Audience :: Developers
Classifier: Intended Audience :: Science/Research
Classifier: License :: OSI Approved :: MIT License
Classifier: Operating System :: OS Independent
Classifier: Programming Language :: Python :: 3
Classifier: Programming Language :: Python :: 3.9
Classifier: Programming Language :: Python :: 3.10
Classifier: Programming Language :: Python :: 3.11
Classifier: Programming Language :: Python :: 3.12
Classifier: Topic :: Scientific/Engineering :: Artificial Intelligence
Classifier: Topic :: Software Development :: Libraries :: Python Modules
Classifier: Topic :: Multimedia :: Sound/Audio :: Speech
Classifier: Topic :: Multimedia :: Graphics :: 3D Modeling
Requires-Python: >=3.9
License-File: LICENSE
Requires-Dist: fastapi>=0.104.0
Requires-Dist: uvicorn[standard]>=0.24.0
Requires-Dist: sqlalchemy>=2.0.0
Requires-Dist: aiosqlite>=0.19.0
Requires-Dist: greenlet>=3.0.0
Requires-Dist: pydantic>=2.5.0
Requires-Dist: pydantic-settings>=2.1.0
Requires-Dist: python-multipart>=0.0.6
Requires-Dist: websockets>=12.0
Requires-Dist: python-dotenv>=1.0.0
Requires-Dist: typer>=0.9.0
Requires-Dist: rich>=13.0.0
Requires-Dist: httpx>=0.25.0
Requires-Dist: requests>=2.31.0
Requires-Dist: jinja2>=3.1.0
Requires-Dist: numpy<2.0.0,>=1.24.0
Requires-Dist: cryptography>=41.0.0
Requires-Dist: aiofiles>=23.0.0
Requires-Dist: edge-tts>=6.1.0
Requires-Dist: huggingface-hub>=0.20.0
Provides-Extra: dev
Requires-Dist: pytest>=7.0.0; extra == "dev"
Requires-Dist: pytest-asyncio>=0.21.0; extra == "dev"
Requires-Dist: black>=23.0.0; extra == "dev"
Requires-Dist: isort>=5.12.0; extra == "dev"
Requires-Dist: flake8>=6.0.0; extra == "dev"
Requires-Dist: mypy>=1.7.0; extra == "dev"
Requires-Dist: pytest-mock>=3.12.0; extra == "dev"
Requires-Dist: pytest-cov>=4.1.0; extra == "dev"
Requires-Dist: httpx>=0.25.0; extra == "dev"
Requires-Dist: pillow>=10.0.0; extra == "dev"
Provides-Extra: ml
Requires-Dist: torch>=2.1.0; extra == "ml"
Requires-Dist: accelerate>=0.24.0; extra == "ml"
Requires-Dist: optimum>=1.14.0; extra == "ml"
Requires-Dist: numpy<2.0.0,>=1.24.0; extra == "ml"
Requires-Dist: mlx>=0.4.0; sys_platform == "darwin" and extra == "ml"
Requires-Dist: mlx-lm>=0.4.0; sys_platform == "darwin" and extra == "ml"
Requires-Dist: huggingface-hub>=0.20.0; extra == "ml"
Provides-Extra: audio
Requires-Dist: soundfile>=0.12.0; extra == "audio"
Requires-Dist: librosa>=0.10.0; extra == "audio"
Requires-Dist: pyaudio>=0.2.11; extra == "audio"
Requires-Dist: numpy<2.0.0,>=1.24.0; extra == "audio"
Requires-Dist: webrtcvad>=2.0.10; extra == "audio"
Requires-Dist: noisereduce>=3.0.0; extra == "audio"
Requires-Dist: openai-whisper>=20231117; extra == "audio"
Provides-Extra: vision
Requires-Dist: opencv-python>=4.8.0; extra == "vision"
Requires-Dist: mediapipe>=0.10.0; extra == "vision"
Requires-Dist: pillow>=10.0.0; extra == "vision"
Requires-Dist: numpy<2.0.0,>=1.24.0; extra == "vision"
Provides-Extra: robotics
Requires-Dist: pyserial>=3.5; extra == "robotics"
Requires-Dist: pybullet>=3.2.5; extra == "robotics"
Requires-Dist: numpy<2.0.0,>=1.24.0; extra == "robotics"
Provides-Extra: security
Requires-Dist: cryptography>=41.0.0; extra == "security"
Requires-Dist: aiofiles>=23.0.0; extra == "security"
Requires-Dist: numpy<2.0.0,>=1.24.0; extra == "security"
Provides-Extra: advanced
Requires-Dist: torch>=2.1.0; extra == "advanced"
Requires-Dist: accelerate>=0.24.0; extra == "advanced"
Requires-Dist: optimum>=1.14.0; extra == "advanced"
Requires-Dist: mlx>=0.4.0; sys_platform == "darwin" and extra == "advanced"
Requires-Dist: mlx-lm>=0.4.0; sys_platform == "darwin" and extra == "advanced"
Requires-Dist: huggingface-hub>=0.20.0; extra == "advanced"
Requires-Dist: soundfile>=0.12.0; extra == "advanced"
Requires-Dist: pyaudio>=0.2.11; extra == "advanced"
Requires-Dist: webrtcvad>=2.0.10; extra == "advanced"
Requires-Dist: noisereduce>=3.0.0; extra == "advanced"
Requires-Dist: edge-tts>=6.1.0; extra == "advanced"
Requires-Dist: opencv-python>=4.8.0; extra == "advanced"
Requires-Dist: mediapipe>=0.10.0; extra == "advanced"
Requires-Dist: pyserial>=3.5; extra == "advanced"
Requires-Dist: pillow>=10.0.0; extra == "advanced"
Requires-Dist: cryptography>=41.0.0; extra == "advanced"
Requires-Dist: aiofiles>=23.0.0; extra == "advanced"
Requires-Dist: scipy>=1.11.0; extra == "advanced"
Requires-Dist: numpy<2.0.0,>=1.24.0; extra == "advanced"
Dynamic: author
Dynamic: home-page
Dynamic: license-file
Dynamic: requires-python
